{

    "configurations": [
        {
            "name": "Linux",
            "includePath": [
                "${workspaceFolder}/**"
            ],
            "defines": [],
            "cStandard": "c20",
            "cppStandard": "gnu++14",
            "intelliSenseMode": "linux-gcc-arm64",
            "browse": {
                "path": [
                    "/home/vscode/Research_Cyclone/Libraries",
                    "/home/vscode/Research_Cyclone"
                ]
            }
        }
    ],
    "version": 4
}